README.md
setup.py
SakuraMysql.egg-info/PKG-INFO
SakuraMysql.egg-info/SOURCES.txt
SakuraMysql.egg-info/dependency_links.txt
SakuraMysql.egg-info/requires.txt
SakuraMysql.egg-info/top_level.txt
sakura/__init__.py
sakura/exception.py
sakura/fields.py
sakura/log.py
sakura/meta.py
sakura/models.py
sakura/mysql.py
sakura/util.py