Metadata-Version: 1.2
Name: SakuraMysql
Version: 0.1.9
Summary: mysql orm
Home-page: https://github.com/SVz777/Sakura
Author: SVz
Author-email: 903943711@qq.com
Maintainer: SVz
Maintainer-email: <903943711@qq.com
License: MIT License
Platform: all
Classifier: Programming Language :: Python :: 3
Classifier: License :: OSI Approved :: MIT License
Classifier: Operating System :: OS Independent
Requires-Python: >=3.6
